DocumentAI_std/__init__.py
DocumentAI_std/base/__init__.py
DocumentAI_std/base/doc_element.py
DocumentAI_std/base/doc_element_classification.py
DocumentAI_std/base/doc_enum.py
DocumentAI_std/base/document.py
DocumentAI_std/base/document_entity_classification.py
DocumentAI_std/data_files/context_words.json
DocumentAI_std/data_files/countries.json
DocumentAI_std/datasets/__init__.py
DocumentAI_std/datasets/cord.py
DocumentAI_std/datasets/funsd.py
DocumentAI_std/datasets/wildreceipt.py
DocumentAI_std/datasets/xfund.py
DocumentAI_std/utils/OCR_adapter.py
DocumentAI_std/utils/__init__.py
DocumentAI_std/utils/base_utils.py
DocumentAI_std/utils/image_utils.py
DocumentAI_std/utils/layout_utils.py
DocumentAI_std/utils/text_utils.py
documentai_std-0.4.0.dist-info/licenses/LICENSE
documentai_std-0.4.0.dist-info/METADATA
documentai_std-0.4.0.dist-info/WHEEL
documentai_std-0.4.0.dist-info/top_level.txt
documentai_std-0.4.0.dist-info/RECORD
