Metadata-Version: 2.4
Name: DocumentAI_std
Version: 0.4.0
Summary: The main standards for Latis Document AI project
Home-page: https://github.com/LATIS-DocumentAI-Group/DocumentAI-std
Author: Hamza Gbada
Author-email: hamza.gbada@gmail.com
License: MIT
Classifier: Programming Language :: Python :: 3.11
Classifier: Programming Language :: Python :: 3.12
Classifier: Programming Language :: Python :: 3.13
Classifier: License :: OSI Approved :: MIT License
Classifier: Operating System :: POSIX :: Linux
Requires-Python: >=3.11, <3.14
License-File: LICENSE
Requires-Dist: pytest==7.4.4
Requires-Dist: easyocr==1.7.1
Requires-Dist: pytesseract==0.3.10
Requires-Dist: numpy>=1.26.3
Requires-Dist: paddleocr==3.1.1
Requires-Dist: Pillow>=10.3
Requires-Dist: PyMuPDF>=1.21.1
Requires-Dist: setuptools
Requires-Dist: paddlepaddle
Requires-Dist: black
Requires-Dist: torch>=2.3.0
Requires-Dist: torchvision>=0.18.0
Requires-Dist: pandas==2.3.1
Requires-Dist: scikit-image~=0.23.2
Requires-Dist: requests~=2.32.3
Requires-Dist: spacy==3.8.7
Dynamic: author
Dynamic: author-email
Dynamic: classifier
Dynamic: description
Dynamic: description-content-type
Dynamic: home-page
Dynamic: license
Dynamic: license-file
Dynamic: requires-dist
Dynamic: requires-python
Dynamic: summary
